dokr_pkg/__init__.py
dokr_pkg/anonymous_matlab.py
dokr_pkg/try1.py
vit1.py-0.1.data/scripts/abc_matlab.py
vit1.py-0.1.data/scripts/anonymous_matlab.py
vit1.py-0.1.data/scripts/try1.py
vit1.py-0.1.data/scripts/vit1.py
vit1.py-0.1.dist-info/METADATA
vit1.py-0.1.dist-info/WHEEL
vit1.py-0.1.dist-info/top_level.txt
vit1.py-0.1.dist-info/RECORD
